{
  "schema": "public",
  "table": "offenses",
  "columns": {
    "OBJECTID": {
      "data_type": "bigint",
      "is_numeric": true
    },
    "Incident Number": {
      "data_type": "text",
      "is_numeric": false,
      "unique_values": [
        "252012327",
        "232043091",
        "242038453",
        "252045704",
        "252047158",
        "252023384",
        "242000112",
        "252069043",
        "242064213",
        "252043859",
        "242108684",
        "252047456",
        "252046356",
        "242023077",
        "232069709",
        "232092983",
        "232059825",
        "232056757",
        "242008189",
        "252018555",
        "242061306",
        "242099997",
        "232069553",
        "232088567",
        "252007351",
        "232060753",
        "252006019",
        "242037579",
        "232055659",
        "242098953",
        "242092595",
        "232079841",
        "252023741",
        "252084424",
        "232071331",
        "252045807",
        "232046153",
        "252037770",
        "232046898",
        "232074571",
        "242007329",
        "232066211",
        "232098096",
        "242033168",
        "232058692",
        "232084507",
        "252068611",
        "252003990",
        "242084986",
        "242085163",
        "232075675",
        "242009149",
        "242107528",
        "242024784",
        "252065786",
        "242091768",
        "242101187",
        "242100502",
        "232082217",
        "232064694",
        "242109909",
        "232093356",
        "232103434",
        "232074778",
        "242061388",
        "232074663",
        "232105105",
        "242020450",
        "232071988",
        "232085389",
        "242040906",
        "252018313",
        "252032838",
        "242090469",
        "242063653",
        "252050213",
        "252041713",
        "232046900",
        "242045125",
        "242005257",
        "252020190",
        "232049526",
        "242021011",
        "232096327",
        "242027091",
        "242109685",
        "252080983",
        "242086890",
        "252049614",
        "222092628",
        "252004343",
        "252018997",
        "242038470",
        "232097104",
        "232054274",
        "252013147",
        "232067682",
        "242091401",
        "252043409",
        "232099290",
        "232043383",
        "232103938",
        "232093447",
        "252019915",
        "242055085",
        "242104684",
        "232052666",
        "252004840",
        "252032750",
        "232089540",
        "252041929",
        "232095725",
        "252068350",
        "242096504",
        "242031660",
        "252037031",
        "252065928",
        "242056050",
        "232080163",
        "252043362",
        "252004107",
        "252044986",
        "242049035",
        "232087896",
        "242093589",
        "240542190",
        "242028671",
        "252020207",
        "242057891",
        "232103691",
        "252020599",
        "232090595",
        "252052344",
        "252035985",
        "242032702",
        "232067756",
        "252060955",
        "242082909",
        "232087952",
        "252081658",
        "252062107",
        "232079875",
        "242050031",
        "252047403",
        "232059407",
        "252046942",
        "242048345",
        "232087282",
        "242016026",
        "242102206",
        "252003748"
      ]
    },
    "Crime": {
      "data_type": "text",
      "is_numeric": false,
      "unique_values": [
        "AUTO THEFT RECOVERY",
        "OTHER",
        "TOWED",
        "AGGRAVATED ASSAULT",
        "MV CRASH RESPONSE",
        "Larceny from MV",
        "LARCENY FROM MV",
        "Other",
        "Vandalism",
        "COUNTERFEITING",
        "Investigate Person",
        "RESTRAINING ORDER VIOLATIONS",
        "Verbal Disputes",
        "Firearm Violations",
        "Property Found",
        "VIOLATIONS",
        "ROBBERY",
        "RESIDENTIAL BURGLARY",
        "CRIMINAL HARASSMENT",
        "PROPERTY FOUND",
        "POLICE SERVICE INCIDENTS",
        "FRAUD",
        "SIMPLE ASSAULT",
        "Property Lost",
        "VANDALISM",
        "LICENSE VIOLATION",
        "WARRANT ARRESTS",
        "Investigate Property",
        "RECOVERED STOLEN PROPERTY",
        "Aggravated Assault",
        "Other Larceny",
        "Robbery",
        "MEDICAL ASSISTANCE",
        "INVESTIGATE PERSON",
        "INVESTIGATE PROPERTY",
        "MISSING PERSON LOCATED",
        "AUTO THEFT",
        "Medical Assistance",
        "VERBAL DISPUTES",
        "INDECENT ASSAULT",
        "OTHER LARCENY",
        "Missing Person Located",
        "MV Crash Response"
      ]
    },
    "Offense Code": {
      "data_type": "text",
      "is_numeric": false
    },
    "Offense Description": {
      "data_type": "text",
      "is_numeric": false
    },
    "Block Address": {
      "data_type": "text",
      "is_numeric": false
    },
    "City": {
      "data_type": "text",
      "is_numeric": false,
      "unique_values": [
        "DORCHESTER",
        "MATTAPAN",
        "BOSTON"
      ]
    },
    "Zip Code": {
      "data_type": "text",
      "is_numeric": false,
      "unique_values": [
        "02124",
        "02126",
        "02125",
        "02122",
        "02127",
        "02121"
      ]
    },
    "BPD District": {
      "data_type": "text",
      "is_numeric": false,
      "unique_values": [
        "B2",
        "B3",
        "C11",
        "C6"
      ]
    },
    "Premise Description": {
      "data_type": "text",
      "is_numeric": false,
      "unique_values": [
        "APARTMENT BUILDING",
        "BAR/ NIGHTCLUB",
        "SCHOOL - ELEMENTARY/ SECONDARY",
        "LIQUOR STORE",
        "GROCERY/ SUPERMARKET",
        "OTHER/UNKNOWN",
        "DRUG STORE/ DOCTOR'S OFFICE/ HOSPITAL",
        "CONVENIENCE STORE",
        "PARKING/ DROP LOT/ GARAGE",
        "COMMERCIAL/ OFFICE BUILDING",
        "AIR/ BUS/ TRAIN TERMINAL",
        "SHOPPING MALL",
        "HIGHWAY/ ROAD/ ALLEY/ STREET/ SIDEWALK",
        "DEPARTMENT/ DISCOUNT/ STORE",
        "GOVERNMENT/ PUBLIC BUILDING",
        "CONSTRUCTION SITE",
        "RESTAURANT",
        "RESIDENCE/ HOME",
        "SERVICE/ GAS STATION"
      ]
    },
    "Weapon Description": {
      "data_type": "text",
      "is_numeric": false,
      "unique_values": [
        "OTHER: PEPPER SPRAY",
        "OTHER: TOSTITOS SALSA JAR",
        "OTHER: FLOWER PITCHER AND CANDLE HOLDER",
        "NONE",
        "PERSONAL WEAPONS (HANDS / FEET)",
        "OTHER: HAND",
        "HANDGUN"
      ]
    },
    "Crime Part": {
      "data_type": "text",
      "is_numeric": false,
      "unique_values": [
        "Part Three",
        "Part Two",
        "Other",
        "Part One"
      ]
    },
    "Crime Category": {
      "data_type": "text",
      "is_numeric": false,
      "unique_values": [
        "Property",
        "Violent"
      ]
    },
    "Report Date": {
      "data_type": "timestamp without time zone",
      "is_numeric": false
    },
    "From Date": {
      "data_type": "timestamp without time zone",
      "is_numeric": false
    },
    "To Date": {
      "data_type": "timestamp without time zone",
      "is_numeric": false
    },
    "Hour of Day": {
      "data_type": "double precision",
      "is_numeric": true
    },
    "Day of Week": {
      "data_type": "double precision",
      "is_numeric": true
    },
    "Year": {
      "data_type": "double precision",
      "is_numeric": true
    },
    "Quarter": {
      "data_type": "double precision",
      "is_numeric": true
    },
    "Month": {
      "data_type": "double precision",
      "is_numeric": true
    },
    "Neighborhood": {
      "data_type": "text",
      "is_numeric": false,
      "unique_values": [
        "Roxbury",
        "Dorchester",
        "Mattapan"
      ]
    }
  }
}